{
    "AX": {
        "error": 0.0067984801838801645,
        "error_type": "SEM",
        "filter_outliers_dict": {
            "filter_outliers": true,
            "iterations": 1,
            "std_devs": 2
        },
        "fit": "Average",
        "fn": 57,
        "include_baseline_error": false,
        "n": 60,
        "reviewed": true,
        "value": -0.031312630250396434
    },
    "CDD": {
        "error": 8.461829411037525e-06,
        "error_type": "SEM",
        "filter_outliers_dict": {
            "filter_outliers": false,
            "iterations": 0,
            "std_devs": 0
        },
        "fit": "Average",
        "fn": 60,
        "include_baseline_error": false,
        "n": 60,
        "reviewed": true,
        "value": 2.7850965125253424e-05
    },
    "H1": {
        "error": 0.004076486827050933,
        "error_type": "SEM",
        "filter_outliers_dict": {
            "filter_outliers": true,
            "iterations": 1,
            "std_devs": 2
        },
        "fit": "Average",
        "fn": 58,
        "include_baseline_error": false,
        "n": 60,
        "reviewed": true,
        "value": 0.005321996660846895
    },
    "H2": {
        "error": 0.015603811487455118,
        "error_type": "SEM",
        "filter_outliers_dict": {
            "filter_outliers": true,
            "iterations": 1,
            "std_devs": 2
        },
        "fit": "average",
        "value": -0.0016374554636910523
    },
    "L1": {
        "error": 0.0027349432789123954,
        "error_type": "SEM",
        "filter_outliers_dict": {
            "filter_outliers": true,
            "iterations": 1,
            "std_devs": 2
        },
        "fit": "Average",
        "fn": 58,
        "include_baseline_error": false,
        "n": 60,
        "reviewed": true,
        "value": -0.05499149210237224
    },
    "L2": {
        "error": 0.006674178872805058,
        "error_type": "SEM",
        "filter_outliers_dict": {
            "filter_outliers": false,
            "iterations": 0,
            "std_devs": 0
        },
        "fit": "Average",
        "fn": 60,
        "include_baseline_error": false,
        "n": 60,
        "reviewed": true,
        "value": -0.044090650983465214
    }
}