{
    "Ar36": {
        "error": 0.0002249363432825061,
        "error_type": "",
        "fit": "previous",
        "references": [
            {
                "exclude": false,
                "record_id": "bu-FC-J-9328"
            }
        ],
        "value": 0.006787287729923903
    },
    "Ar37": {
        "error": 0.005855747677401037,
        "error_type": "",
        "fit": "previous",
        "references": [
            {
                "exclude": false,
                "record_id": "bu-FC-J-9328"
            }
        ],
        "value": 0.038780176427262586
    },
    "Ar38": {
        "error": 0.0024847939398007428,
        "error_type": "",
        "fit": "previous",
        "references": [
            {
                "exclude": false,
                "record_id": "bu-FC-J-9328"
            }
        ],
        "value": 0.011953739820479863
    },
    "Ar39": {
        "error": 0.011166909953647549,
        "error_type": "",
        "fit": "previous",
        "references": [
            {
                "exclude": false,
                "record_id": "bu-FC-J-9328"
            }
        ],
        "value": 0.017572736954835577
    },
    "Ar40": {
        "error": 0.00959179895273251,
        "error_type": "",
        "fit": "previous",
        "references": [
            {
                "exclude": false,
                "record_id": "bu-FC-J-9328"
            }
        ],
        "value": 1.2007003138164996
    },
    "Ar41": {
        "error": 0.014695804689791227,
        "error_type": "",
        "fit": "previous",
        "references": [
            {
                "exclude": false,
                "record_id": "bu-FC-J-9328"
            }
        ],
        "value": 0.02838381331369816
    }
}