{
    "Ar36": {
        "error": 0.00022897529642595444,
        "error_type": "",
        "fit": "previous",
        "references": [
            {
                "exclude": false,
                "record_id": "bu-FC-J-9333"
            }
        ],
        "value": 0.005046237609205508
    },
    "Ar37": {
        "error": 0.00574399749758391,
        "error_type": "",
        "fit": "previous",
        "references": [
            {
                "exclude": false,
                "record_id": "bu-FC-J-9333"
            }
        ],
        "value": 0.04920525659361759
    },
    "Ar38": {
        "error": 0.0026901637911770637,
        "error_type": "",
        "fit": "previous",
        "references": [
            {
                "exclude": false,
                "record_id": "bu-FC-J-9333"
            }
        ],
        "value": 0.007671319394353941
    },
    "Ar39": {
        "error": 0.012091529745968438,
        "error_type": "",
        "fit": "previous",
        "references": [
            {
                "exclude": false,
                "record_id": "bu-FC-J-9333"
            }
        ],
        "value": 0.01925092532184413
    },
    "Ar40": {
        "error": 0.009831965084217357,
        "error_type": "",
        "fit": "previous",
        "references": [
            {
                "exclude": false,
                "record_id": "bu-FC-J-9333"
            }
        ],
        "value": 0.7992771969607663
    },
    "Ar41": {
        "error": 0.013995346231366793,
        "error_type": "",
        "fit": "previous",
        "references": [
            {
                "exclude": false,
                "record_id": "bu-FC-J-9333"
            }
        ],
        "value": 0.024578162751451135
    }
}