{
    "Ar36": {
        "error": 0.0016876474499740958,
        "error_type": "SEM",
        "filter_outliers_dict": {
            "filter_outliers": true,
            "iterations": 1,
            "std_devs": 2
        },
        "fit": "Parabolic",
        "fn": 328,
        "include_baseline_error": false,
        "n": 340,
        "reviewed": true,
        "value": 0.40744667004948243
    },
    "Ar37": {
        "error": 0.015978727625419575,
        "error_type": "SEM",
        "filter_outliers_dict": {
            "filter_outliers": true,
            "iterations": 1,
            "std_devs": 2
        },
        "fit": "Linear",
        "fn": 325,
        "include_baseline_error": false,
        "n": 340,
        "reviewed": true,
        "value": 60.69370181168054
    },
    "Ar38": {
        "error": 0.004960060501209305,
        "error_type": "SEM",
        "filter_outliers_dict": {
            "filter_outliers": true,
            "iterations": 1,
            "std_devs": 2
        },
        "fit": "Linear",
        "fn": 320,
        "include_baseline_error": false,
        "n": 340,
        "reviewed": true,
        "value": 2.9694108121875433
    },
    "Ar39": {
        "error": 0.0372739001341373,
        "error_type": "SEM",
        "filter_outliers_dict": {
            "filter_outliers": true,
            "iterations": 1,
            "std_devs": 2
        },
        "fit": "Parabolic",
        "fn": 330,
        "include_baseline_error": false,
        "n": 340,
        "reviewed": true,
        "value": 113.71802653359522
    },
    "Ar40": {
        "error": 0.04705021926174995,
        "error_type": "SEM",
        "filter_outliers_dict": {
            "filter_outliers": true,
            "iterations": 1,
            "std_devs": 2
        },
        "fit": "Parabolic",
        "fn": 323,
        "include_baseline_error": false,
        "n": 340,
        "reviewed": true,
        "value": 410.80288466761647
    }
}