{
    "Ar36": {
        "error": 0.0015885798541554943,
        "error_type": "SEM",
        "filter_outliers_dict": {
            "filter_outliers": true,
            "iterations": 1,
            "std_devs": 2
        },
        "fit": "Parabolic",
        "fn": 326,
        "include_baseline_error": false,
        "n": 340,
        "reviewed": true,
        "value": 0.34499149396344164
    },
    "Ar37": {
        "error": 0.012837650484083732,
        "error_type": "SEM",
        "filter_outliers_dict": {
            "filter_outliers": true,
            "iterations": 1,
            "std_devs": 2
        },
        "fit": "Linear",
        "fn": 323,
        "include_baseline_error": false,
        "n": 340,
        "reviewed": true,
        "value": 0.39726167814574087
    },
    "Ar38": {
        "error": 0.004744320572355066,
        "error_type": "SEM",
        "filter_outliers_dict": {
            "filter_outliers": true,
            "iterations": 1,
            "std_devs": 2
        },
        "fit": "Linear",
        "fn": 327,
        "include_baseline_error": false,
        "n": 340,
        "reviewed": true,
        "value": 1.376468495552905
    },
    "Ar39": {
        "error": 0.03521539232460547,
        "error_type": "SEM",
        "filter_outliers_dict": {
            "filter_outliers": true,
            "iterations": 1,
            "std_devs": 2
        },
        "fit": "Parabolic",
        "fn": 325,
        "include_baseline_error": false,
        "n": 340,
        "reviewed": true,
        "value": 107.70084965146762
    },
    "Ar40": {
        "error": 0.05251521059925083,
        "error_type": "SEM",
        "filter_outliers_dict": {
            "filter_outliers": true,
            "iterations": 1,
            "std_devs": 2
        },
        "fit": "Parabolic",
        "fn": 323,
        "include_baseline_error": false,
        "n": 340,
        "reviewed": true,
        "value": 549.1715629789664
    }
}