{
    "Ar36": {
        "error": 0.0007743389791463331,
        "error_type": "SEM",
        "filter_outliers_dict": {
            "filter_outliers": true,
            "iterations": 1,
            "std_devs": 2
        },
        "fit": "Linear",
        "fn": 116,
        "include_baseline_error": false,
        "n": 120,
        "reviewed": true,
        "value": 0.09852305071710556
    },
    "Ar37": {
        "error": 0.010153490495093107,
        "error_type": "SEM",
        "filter_outliers_dict": {
            "filter_outliers": true,
            "iterations": 1,
            "std_devs": 2
        },
        "fit": "Linear",
        "fn": 118,
        "include_baseline_error": false,
        "n": 120,
        "reviewed": true,
        "value": 1.2549914759285654
    },
    "Ar38": {
        "error": 0.004237212755001745,
        "error_type": "SEM",
        "filter_outliers_dict": {
            "filter_outliers": true,
            "iterations": 1,
            "std_devs": 2
        },
        "fit": "Linear",
        "fn": 111,
        "include_baseline_error": false,
        "n": 120,
        "reviewed": true,
        "value": 1.1309211445662757
    },
    "Ar39": {
        "error": 0.021601788477147898,
        "error_type": "SEM",
        "filter_outliers_dict": {
            "filter_outliers": true,
            "iterations": 1,
            "std_devs": 2
        },
        "fit": "Linear",
        "fn": 117,
        "include_baseline_error": false,
        "n": 120,
        "reviewed": true,
        "value": 89.5643236444206
    },
    "Ar40": {
        "error": 0.02921899642845515,
        "error_type": "SEM",
        "filter_outliers_dict": {
            "filter_outliers": true,
            "iterations": 1,
            "std_devs": 2
        },
        "fit": "Linear",
        "fn": 116,
        "include_baseline_error": false,
        "n": 120,
        "reviewed": true,
        "value": 323.96562079009925
    },
    "Ar41": {
        "error": 0.009714530899563766,
        "error_type": "SEM",
        "filter_outliers_dict": {
            "filter_outliers": true,
            "iterations": 1,
            "std_devs": 2
        },
        "fit": "Average",
        "value": 0.0570840393919643
    }
}