{
    "Ar36": {
        "error": 0.00021333774717599018,
        "error_type": "SEM",
        "filter_outliers_dict": {
            "filter_outliers": true,
            "iterations": 1,
            "std_devs": 2
        },
        "fit": "Linear",
        "fn": 115,
        "include_baseline_error": false,
        "n": 120,
        "reviewed": true,
        "value": 0.005916235804149513
    },
    "Ar37": {
        "error": 0.009659412931205867,
        "error_type": "SEM",
        "filter_outliers_dict": {
            "filter_outliers": true,
            "iterations": 1,
            "std_devs": 2
        },
        "fit": "Linear",
        "fn": 113,
        "include_baseline_error": false,
        "n": 120,
        "reviewed": true,
        "value": 0.635658903224988
    },
    "Ar38": {
        "error": 0.005295937286358934,
        "error_type": "SEM",
        "filter_outliers_dict": {
            "filter_outliers": true,
            "iterations": 1,
            "std_devs": 2
        },
        "fit": "Linear",
        "fn": 115,
        "include_baseline_error": false,
        "n": 120,
        "reviewed": true,
        "value": 0.39050144736372316
    },
    "Ar39": {
        "error": 0.014628403751490417,
        "error_type": "SEM",
        "filter_outliers_dict": {
            "filter_outliers": true,
            "iterations": 1,
            "std_devs": 2
        },
        "fit": "Linear",
        "fn": 113,
        "include_baseline_error": false,
        "n": 120,
        "reviewed": true,
        "value": 33.74101932722539
    },
    "Ar40": {
        "error": 0.019738935921684627,
        "error_type": "SEM",
        "filter_outliers_dict": {
            "filter_outliers": true,
            "iterations": 1,
            "std_devs": 2
        },
        "fit": "Linear",
        "fn": 112,
        "include_baseline_error": false,
        "n": 120,
        "reviewed": true,
        "value": 122.18296085943764
    },
    "Ar41": {
        "error": 0.009861783668076798,
        "error_type": "SEM",
        "filter_outliers_dict": {
            "filter_outliers": true,
            "iterations": 1,
            "std_devs": 2
        },
        "fit": "Average",
        "value": 0.04889799246801879
    }
}